heimdallsword/__init__.py
heimdallsword/__main__.py
heimdallsword/release.py
heimdallsword/status.py
heimdallsword/data/__init__.py
heimdallsword/data/config.py
heimdallsword/data/metrics.py
heimdallsword/dispatcher/__init__.py
heimdallsword/dispatcher/client.py
heimdallsword/dispatcher/orchestrator.py
heimdallsword/dispatcher/subscriber.py
heimdallsword/graphics/__init__.py
heimdallsword/graphics/renderer.py
heimdallsword/log/__init__.py
heimdallsword/log/cli_log.py
heimdallsword/log/handler.py
heimdallsword/models/__init__.py
heimdallsword/models/message.py
heimdallsword/models/recipient.py
heimdallsword/models/sender.py
heimdallsword/utils/__init__.py
heimdallsword/utils/parser.py
heimdallsword/utils/util.py
heimdallsword-0.0.2.dist-info/LICENSE
heimdallsword-0.0.2.dist-info/METADATA
heimdallsword-0.0.2.dist-info/WHEEL
heimdallsword-0.0.2.dist-info/entry_points.txt
heimdallsword-0.0.2.dist-info/top_level.txt
heimdallsword-0.0.2.dist-info/RECORD
