Metadata-Version: 2.1
Name: heimdallsword
Version: 0.0.2
Summary: A tool for sending emails to multiple recipients using one or multiple sender accounts with customizable email templates.
Home-page: http://github.com/rwprimitives/heimdallsword
Author: eldiablo
Author-email: avsarria@gmail.com
License: BSD-3-Clause
Project-URL: Source, http://github.com/rwprimitives/tor-seeker
Project-URL: Bug Tracker, https://github.com/rwprimitives/tor-seeker/issues
Keywords: tor,relay,network,ip,anonymity
Platform: any
Classifier: Development Status :: 5 - Production/Stable
Classifier: Intended Audience :: Customer Service
Classifier: Intended Audience :: Developers
Classifier: Intended Audience :: End Users/Desktop
Classifier: Intended Audience :: Information Technology
Classifier: Intended Audience :: Other Audience
Classifier: Intended Audience :: Science/Research
Classifier: Intended Audience :: System Administrators
Classifier: Intended Audience :: Telecommunications Industry
Classifier: Operating System :: OS Independent
Classifier: Topic :: Communications
Classifier: Topic :: Communications :: Email
Classifier: Topic :: Communications :: Email :: Mailing List Servers
Classifier: Topic :: Communications :: Email :: Post-Office
Classifier: Topic :: Internet
Classifier: Topic :: Scientific/Engineering
Classifier: Topic :: System :: Networking
Classifier: License :: OSI Approved :: BSD License
Classifier: Natural Language :: English
Classifier: Programming Language :: Python :: 3.6
Classifier: Programming Language :: Python :: 3.7
Classifier: Programming Language :: Python :: 3.8
Classifier: Programming Language :: Python :: 3.9
Classifier: Programming Language :: Python :: 3.10
Classifier: Programming Language :: Python :: 3.11
Classifier: Programming Language :: Python :: Implementation
Classifier: Programming Language :: Python :: Implementation :: CPython
Requires-Python: >=3.6
License-File: LICENSE
Provides-Extra: codestyle
Requires-Dist: flake8 (<4,>=3) ; extra == 'codestyle'
